scikits/__init__.py
scikits/fitting/__init__.py
scikits/fitting/delaunay.py
scikits/fitting/gaussian.py
scikits/fitting/generic.py
scikits/fitting/linlstsq.py
scikits/fitting/nonlinlstsq.py
scikits/fitting/poly.py
scikits/fitting/rbf.py
scikits/fitting/spline.py
scikits/fitting/utils.py
scikits/fitting/tests/__init__.py
scikits/fitting/tests/test_delaunay.py
scikits/fitting/tests/test_gaussian.py
scikits/fitting/tests/test_generic.py
scikits/fitting/tests/test_linlstsq.py
scikits/fitting/tests/test_nonlinlstsq.py
scikits/fitting/tests/test_poly.py
scikits/fitting/tests/test_rbf.py
scikits/fitting/tests/test_spline.py
scikits/fitting/tests/test_utils.py
scikits.fitting-0.7.2.dist-info/LICENSE.txt
scikits.fitting-0.7.2.dist-info/METADATA
scikits.fitting-0.7.2.dist-info/WHEEL
scikits.fitting-0.7.2.dist-info/top_level.txt
scikits.fitting-0.7.2.dist-info/RECORD
