Metadata-Version: 2.1
Name: scikits.fitting
Version: 0.7.2
Summary: Framework for fitting functions to data with SciPy
Home-page: https://github.com/ska-sa/scikits.fitting
Maintainer: Ludwig Schwardt
Maintainer-email: ludwig@ska.ac.za
License: Modified BSD
Platform: OS Independent
Classifier: Development Status :: 5 - Production/Stable
Classifier: Environment :: Console
Classifier: Intended Audience :: Developers
Classifier: Intended Audience :: Science/Research
Classifier: License :: OSI Approved :: BSD License
Classifier: Operating System :: OS Independent
Classifier: Programming Language :: Python
Classifier: Programming Language :: Python :: 2
Classifier: Programming Language :: Python :: 2.7
Classifier: Programming Language :: Python :: 3
Classifier: Topic :: Software Development :: Libraries :: Python Modules
Classifier: Topic :: Scientific/Engineering
Requires-Python: >=2.7, !=3.0, !=3.1, !=3.2, <4
License-File: LICENSE.txt
Requires-Dist: numpy
Requires-Dist: scipy >=0.9
Requires-Dist: future
